odoo/addons/mail_partner_forwarding/README.rst
odoo/addons/mail_partner_forwarding/__init__.py
odoo/addons/mail_partner_forwarding/__manifest__.py
odoo/addons/mail_partner_forwarding/i18n/mail_partner_forwarding.pot
odoo/addons/mail_partner_forwarding/models/__init__.py
odoo/addons/mail_partner_forwarding/models/mail_thread.py
odoo/addons/mail_partner_forwarding/models/res_partner.py
odoo/addons/mail_partner_forwarding/models/res_user.py
odoo/addons/mail_partner_forwarding/readme/CONTRIBUTORS.rst
odoo/addons/mail_partner_forwarding/readme/DESCRIPTION.rst
odoo/addons/mail_partner_forwarding/readme/HISTORY.rst
odoo/addons/mail_partner_forwarding/readme/USAGE.rst
odoo/addons/mail_partner_forwarding/static/description/icon.png
odoo/addons/mail_partner_forwarding/static/description/index.html
odoo/addons/mail_partner_forwarding/tests/__init__.py
odoo/addons/mail_partner_forwarding/tests/test_mail_forwarding.py
odoo/addons/mail_partner_forwarding/tests/models/__init__.py
odoo/addons/mail_partner_forwarding/tests/models/fake_order.py
odoo/addons/mail_partner_forwarding/views/res_partner_views.xml
odoo/addons/mail_partner_forwarding/views/res_user_views.xml
odoo13_addon_mail_partner_forwarding-13.0.1.0.1.dev4.dist-info/METADATA
odoo13_addon_mail_partner_forwarding-13.0.1.0.1.dev4.dist-info/WHEEL
odoo13_addon_mail_partner_forwarding-13.0.1.0.1.dev4.dist-info/top_level.txt
odoo13_addon_mail_partner_forwarding-13.0.1.0.1.dev4.dist-info/RECORD
